setup.cfg
setup.py
git_orm/__init__.py
git_orm/importer.py
git_orm/quote.py
git_orm/serializer.py
git_orm/sync.py
git_orm/testcases.py
git_orm/transaction.py
git_orm.egg-info/PKG-INFO
git_orm.egg-info/SOURCES.txt
git_orm.egg-info/dependency_links.txt
git_orm.egg-info/requires.txt
git_orm.egg-info/top_level.txt
git_orm/models/__init__.py
git_orm/models/base.py
git_orm/models/fields.py
git_orm/models/options.py
git_orm/models/query.py
git_orm/models/queryset.py