Metadata-Version: 1.1
Name: git-orm
Version: 0.4
Summary: object-relational mapper for the git object store
Home-page: http://github.com/natano/git-orm/
Author: Martin Natano
Author-email: natano@natano.net
License: ISC
Keywords: Git,Distributed,ORM,Relational
Platform: UNKNOWN
Classifier: Intended Audience :: Developers
Classifier: License :: OSI Approved :: ISC License (ISCL)
Classifier: Programming Language :: Python
Classifier: Programming Language :: Python :: 3.2
Classifier: Programming Language :: Python :: 3.3
Classifier: Topic :: Database
Classifier: Topic :: Software Development :: Version Control
Classifier: Topic :: Software Development :: Libraries :: Python Modules
Classifier: Development Status :: 3 - Alpha
